[
  {
    "Atributo": "cod_caixa",
    "Tipo": "number",
    "Tamanho": 15,
    "Descricao": "Código da caixa",
    "Obrigatoriedade": "sim",
    "Observacoes": "primary key"
  },
  {
    "Atributo": "cod_tamanho",
    "Tipo": "varchar",
    "Tamanho": 50,
    "Descricao": "Chave para tabela tamanho",
    "Obrigatoriedade": "sim",
    "Observacoes": ""
  },
  {
    "Atributo": "cod_local",
    "Tipo": "varchar",
    "Tamanho": 50,
    "Descricao": "Chave para tabela local",
    "Obrigatoriedade": "sim",
    "Observacoes": ""
  },
  {
    "Atributo": "status",
    "Tipo": "enum",
    "Tamanho": 50,
    "Descricao": "Situações que o registro pode assumir V-Vazia, C-Cheia, ao eliminar (colocar status = ‘D’) uma caixa, acrescentar 1 na\nQuantidade disponível do local.\nao incluir uma caixa, reduzir 1 na Quantidade disponível do local",
    "Obrigatoriedade": "sim",
    "Observacoes": "'V', 'C'"
  }
]
